pylogcounter/__init__.py
pylogcounter/cli.py
pylogcounter/counter.py
pylogcounter/parse.py
pylogcounter/stat.py
pylogcounter/writer.py
pylogcounter-0.2.0.dist-info/LICENSE
pylogcounter-0.2.0.dist-info/METADATA
pylogcounter-0.2.0.dist-info/WHEEL
pylogcounter-0.2.0.dist-info/entry_points.txt
pylogcounter-0.2.0.dist-info/top_level.txt
pylogcounter-0.2.0.dist-info/RECORD
