Metadata-Version: 2.1
Name: pylogcounter
Version: 0.2.0
Summary: "CLI for checking timely lines and size of a log file."
Author: git-ogawa
Author-email: stu1232541964@gmail.com
Keywords: python,log
Classifier: Programming Language :: Python :: 3
Classifier: Programming Language :: Python :: 3 :: Only
Classifier: Programming Language :: Python :: 3.8
Classifier: Programming Language :: Python :: 3.9
Classifier: Programming Language :: Python :: 3.10
Classifier: Programming Language :: Python :: 3.11
Requires-Python: >=3.8
License-File: LICENSE
Requires-Dist: pyyaml (>=6.0)
Requires-Dist: pandas (>=1.5.2)
Provides-Extra: dev
Requires-Dist: flake8 ; extra == 'dev'
Requires-Dist: mypy ; extra == 'dev'
Requires-Dist: black ; extra == 'dev'
Requires-Dist: isort ; extra == 'dev'
Requires-Dist: pytest ; extra == 'dev'
Requires-Dist: types-PyYAML ; extra == 'dev'
